kosu/__init__.py
kosu/__main__.py
kosu/_version.py
kosu/customize.py
kosu/kosu.py
kosu/include/.kosu.yaml
kosu/include/Interesting_notebook.ipynb
kosu/include/Intro_to_Matplotlib.ipynb
kosu/include/Intro_to_NumPy.ipynb
kosu/include/Intro_to_Python.ipynb
kosu/include/README.md
kosu/include/environment.yaml
kosu/include/example.png
kosu/include/example.py
kosu/include/example_course.yaml
kosu/include/tops.txt
kosu/include/useful.pdf
kosu-0.1.6.dist-info/AUTHORS.md
kosu-0.1.6.dist-info/LICENSE
kosu-0.1.6.dist-info/METADATA
kosu-0.1.6.dist-info/WHEEL
kosu-0.1.6.dist-info/entry_points.txt
kosu-0.1.6.dist-info/top_level.txt
kosu-0.1.6.dist-info/RECORD
